tensorbase_client/__init__.py
tensorbase_client/_base_client.py
tensorbase_client/_client.py
tensorbase_client/_compat.py
tensorbase_client/_constants.py
tensorbase_client/_exceptions.py
tensorbase_client/_files.py
tensorbase_client/_models.py
tensorbase_client/_qs.py
tensorbase_client/_resource.py
tensorbase_client/_response.py
tensorbase_client/_streaming.py
tensorbase_client/_types.py
tensorbase_client/_version.py
tensorbase_client/py.typed
tensorbase_client/_utils/__init__.py
tensorbase_client/_utils/_logs.py
tensorbase_client/_utils/_proxy.py
tensorbase_client/_utils/_reflection.py
tensorbase_client/_utils/_resources_proxy.py
tensorbase_client/_utils/_streams.py
tensorbase_client/_utils/_sync.py
tensorbase_client/_utils/_transform.py
tensorbase_client/_utils/_typing.py
tensorbase_client/_utils/_utils.py
tensorbase_client/lib/.keep
tensorbase_client/resources/__init__.py
tensorbase_client/resources/chat.py
tensorbase_client/resources/images.py
tensorbase_client/resources/models.py
tensorbase_client/types/__init__.py
tensorbase_client/types/chat_generate_completion_params.py
tensorbase_client/types/chat_generate_completion_response.py
tensorbase_client/types/health_check_response.py
tensorbase_client/types/image_generate_params.py
tensorbase_client/types/image_generate_response.py
tensorbase_client/types/model_list_response.py
tensorbase_client/types/model_retrieve_response.py
tensorbase_client-0.1.0a3.dist-info/METADATA
tensorbase_client-0.1.0a3.dist-info/WHEEL
tensorbase_client-0.1.0a3.dist-info/licenses/LICENSE
tensorbase_client-0.1.0a3.dist-info/RECORD
